{"code": 0, "data": {"collectionMetadata": {"collectionId": "2114", "createdAt": "2023-07-31T18:23:18+08:00", "name": "Amendment to MP2014 Rail Station", "description": "Indicative outline of the MRT, LRT stations.", "lastUpdatedAt": "2024-06-06T14:54:25+08:00", "frequency": "ad-hoc", "sources": ["Urban Redevelopment Authority"], "managedBy": "Urban Redevelopment Authority", "childDatasets": ["d_af90df38d609c426c73bc9acea366786", "d_0a39b2bbb83a5b0efc50a71ca7a19e7f"]}, "datasetMetadata": [{"datasetId": "d_af90df38d609c426c73bc9acea366786", "createdAt": "2023-07-31T18:24:01+08:00", "name": "Amendment to MP2014 Rail Station", "collectionIds": ["2114"], "format": "GEOJSON", "lastUpdatedAt": "2024-06-06T14:54:25+08:00", "managedBy": "Urban Redevelopment Authority"}, {"datasetId": "d_0a39b2bbb83a5b0efc50a71ca7a19e7f", "createdAt": "2023-07-31T18:24:04+08:00", "name": "Amendment to MP2014 Rail Station", "collectionIds": ["2114"], "format": "KML", "lastUpdatedAt": "2024-06-06T14:22:26+08:00", "managedBy": "Urban Redevelopment Authority"}]}, "errorMsg": ""}