{"code": 0, "data": {"collectionMetadata": {"collectionId": "102", "createdAt": "2016-05-30T09:50:51+08:00", "name": "Common health problems of students examined - Defective Vision, Annual", "description": "Number of students with visual acuity - VA (Snellen) \u2265 6/12 or VA (LogMAR) \u2265 0.30 for male and female students", "lastUpdatedAt": "2024-06-06T15:01:03+08:00", "coverageStart": "2009-01-01T08:00:00+08:00", "coverageEnd": "2020-12-31T08:00:00+08:00", "frequency": "annual", "sources": ["Health Promotion Board"], "managedBy": "Health Promotion Board", "childDatasets": ["d_d05099460f780ed9c7b7824540872ea2"]}, "datasetMetadata": [{"datasetId": "d_d05099460f780ed9c7b7824540872ea2", "createdAt": "2016-05-30T17:52:30+08:00", "name": "Common health problems of students examined - Defective Vision, Annual", "collectionIds": ["102"], "format": "CSV", "lastUpdatedAt": "2024-06-06T15:01:03+08:00", "managedBy": "Health Promotion Board", "coverageStart": "2009-01-01T08:00:00+08:00", "coverageEnd": "2020-12-31T08:00:00+08:00"}]}, "errorMsg": ""}