{"code": 0, "data": {"collectionMetadata": {"collectionId": "1443", "createdAt": "2015-10-20T13:54:35+08:00", "name": "E-waste Recycling", "description": "E-waste recycling near you.", "lastUpdatedAt": "2024-06-06T15:02:58+08:00", "frequency": "annual", "sources": ["National Environment Agency"], "managedBy": "National Environment Agency", "childDatasets": ["d_db40d004afeb5a7f0f555fdcc34934cc", "d_243a551f32af0c176251b26952d66a0c"]}, "datasetMetadata": [{"datasetId": "d_db40d004afeb5a7f0f555fdcc34934cc", "createdAt": "2018-11-27T00:00:00+08:00", "name": "E-waste Recycling (GEOJSON)", "collectionIds": ["1443"], "format": "GEOJSON", "lastUpdatedAt": "2024-06-06T15:02:58+08:00", "managedBy": "National Environment Agency"}, {"datasetId": "d_243a551f32af0c176251b26952d66a0c", "createdAt": "2016-03-24T00:00:00+08:00", "name": "E-waste Recycling (KML)", "collectionIds": ["1443"], "format": "KML", "lastUpdatedAt": "2024-06-06T14:27:36+08:00", "managedBy": "National Environment Agency"}]}, "errorMsg": ""}