{"code": 0, "data": {"collectionMetadata": {"collectionId": "93", "createdAt": "2022-09-07T14:44:27+08:00", "name": "List of Services in Canberra", "description": "List of Services in Canberra", "lastUpdatedAt": "2024-06-06T15:04:08+08:00", "coverageStart": "2022-09-07T08:00:00+08:00", "coverageEnd": "2022-09-07T08:00:00+08:00", "frequency": "ad-hoc", "sources": ["Government Technology Agency"], "managedBy": "Government Technology Agency", "childDatasets": ["d_e0f04bf64a2beee4b9689d00e7278f86"]}, "datasetMetadata": [{"datasetId": "d_e0f04bf64a2beee4b9689d00e7278f86", "createdAt": "2022-09-07T14:45:03+08:00", "name": "List of Services in Canberra", "collectionIds": ["93"], "format": "CSV", "lastUpdatedAt": "2024-06-06T15:04:08+08:00", "managedBy": "Government Technology Agency", "coverageStart": "2022-09-07T08:00:00+08:00", "coverageEnd": "2022-09-07T08:00:00+08:00"}]}, "errorMsg": ""}