{"code": 0, "data": {"collectionMetadata": {"collectionId": "1775", "createdAt": "2017-06-14T16:09:54+08:00", "name": "MP14 SDCP AGU PLAN - 1st Storey (Encouraged)", "description": "Indicative location of the 1st Storey Activites (Encourage) area.", "lastUpdatedAt": "2024-06-06T14:55:08+08:00", "frequency": "ad-hoc", "sources": ["Urban Redevelopment Authority"], "managedBy": "Urban Redevelopment Authority", "childDatasets": ["d_50d6c1eeed7d64f6654b00df2059dfb7", "d_b2a1dc03b58ab69525ff8df05d90bab2"]}, "datasetMetadata": [{"datasetId": "d_50d6c1eeed7d64f6654b00df2059dfb7", "createdAt": "2014-07-03T00:00:00+08:00", "name": "MP14 SDCP AGU PLAN - 1st Storey (Encouraged) (KML)", "collectionIds": ["1775"], "format": "KML", "lastUpdatedAt": "2024-06-06T14:36:01+08:00", "managedBy": "Urban Redevelopment Authority"}, {"datasetId": "d_b2a1dc03b58ab69525ff8df05d90bab2", "createdAt": "2014-07-03T00:00:00+08:00", "name": "MP14 SDCP AGU PLAN - 1st Storey (Encouraged) (SHP)", "collectionIds": ["1775"], "format": "SHP", "lastUpdatedAt": "2024-06-06T14:55:08+08:00", "managedBy": "Urban Redevelopment Authority"}]}, "errorMsg": ""}