{"code": 0, "data": {"collectionMetadata": {"collectionId": "1497", "createdAt": "2018-05-22T15:50:26+08:00", "name": "Ngee Ann Polytechnic Financial Assistance Schemes", "description": "This dataset contains the detailed eligibility, quantum and conditions of the financial assistance available in Ngee Ann Polytechnic.", "lastUpdatedAt": "2024-06-06T15:09:18+08:00", "coverageStart": "2019-01-01T08:00:00+08:00", "coverageEnd": "2022-12-31T08:00:00+08:00", "frequency": "annual", "sources": ["Ngee Ann Polytechnic"], "managedBy": "Ngee Ann Polytechnic", "childDatasets": ["d_dbf365a8ab12d47f97113dd270bf10f0", "d_5711f5307bc216e7588b768cd9ad6dae", "d_57e85ac72c257c08ebbe8c59b494c114", "d_f98b0d0bf644c30ce95129f95a947b9c"]}, "datasetMetadata": [{"datasetId": "d_dbf365a8ab12d47f97113dd270bf10f0", "createdAt": "2022-12-28T17:43:40+08:00", "name": "2022 Financial Assistance Schemes", "collectionIds": ["1497"], "description": "2022 Financial Assistance Schemes", "format": "CSV", "lastUpdatedAt": "2024-06-06T15:03:06+08:00", "managedBy": "Ngee Ann Polytechnic", "coverageStart": "2022-01-01T08:00:00+08:00", "coverageEnd": "2022-12-31T08:00:00+08:00"}, {"datasetId": "d_5711f5307bc216e7588b768cd9ad6dae", "createdAt": "2021-11-25T15:12:58+08:00", "name": "2019 Financial Assistance Schemes", "collectionIds": ["1497"], "description": "2019 Financial Assistance Schemes", "format": "CSV", "lastUpdatedAt": "2024-06-06T14:37:16+08:00", "managedBy": "Ngee Ann Polytechnic", "coverageStart": "2019-01-01T08:00:00+08:00", "coverageEnd": "2019-12-31T08:00:00+08:00"}, {"datasetId": "d_57e85ac72c257c08ebbe8c59b494c114", "createdAt": "2021-11-24T18:22:52+08:00", "name": "2021 Financial Assistance Schemes", "collectionIds": ["1497"], "description": "2021 Financial Assistance Schemes", "format": "CSV", "lastUpdatedAt": "2024-06-06T14:37:25+08:00", "managedBy": "Ngee Ann Polytechnic", "coverageStart": "2021-01-01T08:00:00+08:00", "coverageEnd": "2021-12-31T08:00:00+08:00"}, {"datasetId": "d_f98b0d0bf644c30ce95129f95a947b9c", "createdAt": "2018-05-22T15:55:32+08:00", "name": "2020 Financial Assistance Schemes", "collectionIds": ["1497"], "description": "2020 Financial Assistance Schemes", "format": "CSV", "lastUpdatedAt": "2024-06-06T15:09:18+08:00", "managedBy": "Ngee Ann Polytechnic", "coverageStart": "2020-01-01T08:00:00+08:00", "coverageEnd": "2020-12-31T08:00:00+08:00"}]}, "errorMsg": ""}