{"code": 0, "data": {"collectionMetadata": {"collectionId": "558", "createdAt": "2016-04-06T13:48:36+08:00", "name": "Number of Parcels cleared at the Parcel Post Centre", "description": "This table presents the yearly breakdown on the number of parcels cleared at the Parcel Post Centre from 2004 onwards\r\n", "lastUpdatedAt": "2024-06-06T15:22:22+08:00", "coverageStart": "2004-01-01T08:00:00+08:00", "coverageEnd": "2021-12-31T08:00:00+08:00", "frequency": "annual", "sources": ["Immigration and Checkpoints Authority"], "managedBy": "Immigration and Checkpoints Authority", "childDatasets": ["d_6a548606cf9132cb0b68463e0b8fa6a3"]}, "datasetMetadata": [{"datasetId": "d_6a548606cf9132cb0b68463e0b8fa6a3", "createdAt": "2016-04-06T21:49:08+08:00", "name": "Number of Parcels cleared at the Parcel Post Centre", "collectionIds": ["558"], "format": "CSV", "lastUpdatedAt": "2024-06-06T15:22:22+08:00", "managedBy": "Immigration and Checkpoints Authority", "coverageStart": "2004-01-01T08:00:00+08:00", "coverageEnd": "2022-01-01T08:00:00+08:00"}]}, "errorMsg": ""}