{"code": 0, "data": {"collectionMetadata": {"collectionId": "3", "createdAt": "2015-05-20T10:11:24+08:00", "name": "Patents Applied, Awarded and Owned by Sector", "description": "To collect data that provide useful indication on the scale and direction of R&D in Singapore. This will facilitate the development of national science and technology policies and programmes, which will benefit the whole R&D community. \r\n\r\nFor more information, please refer to https://www.a-star.edu.sg/News-and-Events/publications", "lastUpdatedAt": "2024-06-06T14:33:36+08:00", "coverageStart": "2000-01-01T08:00:00+08:00", "coverageEnd": "2018-12-31T08:00:00+08:00", "frequency": "annual", "sources": ["Agency For Science, Technology and Research"], "managedBy": "Agency For Science, Technology and Research", "childDatasets": ["d_455fe9261807a6a0255b2e2fbe188545"]}, "datasetMetadata": [{"datasetId": "d_455fe9261807a6a0255b2e2fbe188545", "createdAt": "2015-05-21T14:10:45+08:00", "name": "Patents Applied, Awarded and Owned by Sector", "collectionIds": ["3"], "format": "CSV", "lastUpdatedAt": "2024-06-06T14:33:36+08:00", "managedBy": "Agency For Science, Technology and Research", "coverageStart": "2000-01-01T08:00:00+08:00", "coverageEnd": "2018-12-31T08:00:00+08:00"}]}, "errorMsg": ""}