{"code": 0, "data": {"collectionMetadata": {"collectionId": "1828", "createdAt": "2017-06-14T16:08:27+08:00", "name": "SDCP Conservation Area Boundary", "description": "Indicative polygon of the Conservation Area boundary.", "lastUpdatedAt": "2024-06-06T14:42:56+08:00", "frequency": "ad-hoc", "sources": ["Urban Redevelopment Authority"], "managedBy": "Urban Redevelopment Authority", "childDatasets": ["d_21152ce0981e3fad7c71d888209d3b83", "d_771034fa6194c93430535299e05d3311"]}, "datasetMetadata": [{"datasetId": "d_21152ce0981e3fad7c71d888209d3b83", "createdAt": "2012-06-21T00:00:00+08:00", "name": "SDCP Conservation Area Boundary (SHP)", "collectionIds": ["1828"], "format": "SHP", "lastUpdatedAt": "2024-06-06T14:27:01+08:00", "managedBy": "Urban Redevelopment Authority"}, {"datasetId": "d_771034fa6194c93430535299e05d3311", "createdAt": "2012-06-21T00:00:00+08:00", "name": "SDCP Conservation Area Boundary (KML)", "collectionIds": ["1828"], "format": "KML", "lastUpdatedAt": "2024-06-06T14:42:56+08:00", "managedBy": "Urban Redevelopment Authority"}]}, "errorMsg": ""}