{"code": 0, "data": {"collectionMetadata": {"collectionId": "1831", "createdAt": "2017-06-14T16:08:47+08:00", "name": "SDCP Landed Housing Area", "description": "Indicative polygon of land housing area boundary.", "lastUpdatedAt": "2024-06-06T15:02:37+08:00", "frequency": "ad-hoc", "sources": ["Urban Redevelopment Authority"], "managedBy": "Urban Redevelopment Authority", "childDatasets": ["d_d915b6ade6868f1d82d5df8bbd639363", "d_8dc00b2b96477944e5f8402ac6edbc31"]}, "datasetMetadata": [{"datasetId": "d_d915b6ade6868f1d82d5df8bbd639363", "createdAt": "2011-04-06T00:00:00+08:00", "name": "SDCP Landed Housing Area (KML)", "collectionIds": ["1831"], "format": "KML", "lastUpdatedAt": "2024-06-06T15:02:37+08:00", "managedBy": "Urban Redevelopment Authority"}, {"datasetId": "d_8dc00b2b96477944e5f8402ac6edbc31", "createdAt": "2011-04-06T00:00:00+08:00", "name": "SDCP Landed Housing Area (SHP)", "collectionIds": ["1831"], "format": "SHP", "lastUpdatedAt": "2024-06-06T14:47:35+08:00", "managedBy": "Urban Redevelopment Authority"}]}, "errorMsg": ""}