{"code": 0, "data": {"collectionMetadata": {"collectionId": "1452", "createdAt": "2015-05-20T10:11:03+08:00", "name": "Surface Air Temperature - Mean Daily Maximum", "description": "The monthly and annual mean daily maximum temperature recorded at the Changi Climate Station.", "lastUpdatedAt": "2025-01-08T16:36:18+08:00", "coverageStart": "1982-01-01T08:00:00+08:00", "coverageEnd": "2023-07-31T08:00:00+08:00", "frequency": "monthly", "sources": ["National Environment Agency"], "managedBy": "National Environment Agency", "childDatasets": ["d_b0fb69de67054d6d741bea78274ecc2a", "d_8e72ca09d5000b490126e3cd492f942b"]}, "datasetMetadata": [{"datasetId": "d_b0fb69de67054d6d741bea78274ecc2a", "createdAt": "2015-05-21T14:13:19+08:00", "name": "Surface Air Temperature - Monthly Mean Daily Maximum", "collectionIds": ["1452"], "description": "Monthly mean daily maximum temperature (in degree Celsius) at the Changi Climate Station. ", "format": "CSV", "lastUpdatedAt": "2025-01-08T16:32:17+08:00", "managedBy": "National Environment Agency", "coverageStart": "1982-01-01T08:00:00+08:00", "coverageEnd": "2024-12-01T08:00:00+08:00"}, {"datasetId": "d_8e72ca09d5000b490126e3cd492f942b", "createdAt": "2015-11-05T21:39:43+08:00", "name": "Surface Air Temperature - Annual Mean Daily Maximum", "collectionIds": ["1452"], "description": "Annual mean daily maximum temperature (in degree Celsius) at the Changi Climate Station. ", "format": "CSV", "lastUpdatedAt": "2025-01-08T16:36:18+08:00", "managedBy": "National Environment Agency", "coverageStart": "1982-01-01T08:00:00+08:00", "coverageEnd": "2024-01-01T08:00:00+08:00"}]}, "errorMsg": ""}