{"code": 0, "data": {"collectionMetadata": {"collectionId": "232", "createdAt": "2016-06-28T20:25:24+08:00", "name": "Weekly Time Spent on Media Activities", "description": "Data extracted from the IMDA Media Consumer Experience Study, an annual survey conducted by IMDA , which aims to provide insights into Singapore Citizens and PRs' media consumption habits.\r\n\r\nFor more information, please visit: \r\nhttps://www.imda.gov.sg/industry-development/facts-and-figures/media-consumer-experience-study", "lastUpdatedAt": "2024-06-06T14:42:15+08:00", "coverageStart": "2011-01-01T08:00:00+08:00", "coverageEnd": "2015-12-31T08:00:00+08:00", "frequency": "annual", "sources": ["Info-communications Media Development Authority"], "managedBy": "Info-communications Media Development Authority", "childDatasets": ["d_73b33e1ddffcfad04b8ca4d3ded59440"]}, "datasetMetadata": [{"datasetId": "d_73b33e1ddffcfad04b8ca4d3ded59440", "createdAt": "2016-06-29T04:36:42+08:00", "name": "Weekly Time Spent on Media Activities", "collectionIds": ["232"], "description": "Respondents were asked for their weekly time spent on various media activities via a face-to-face interview.", "format": "CSV", "lastUpdatedAt": "2024-06-06T14:42:15+08:00", "managedBy": "Info-communications Media Development Authority", "coverageStart": "2011-01-01T08:00:00+08:00", "coverageEnd": "2015-12-31T08:00:00+08:00"}]}, "errorMsg": ""}