{"code": 0, "data": {"collectionMetadata": {"collectionId": "239", "createdAt": "2015-10-22T11:11:47+08:00", "name": "Wireless HotSpots", "description": "To locate Wireless@SG hotspots in Singapore.", "lastUpdatedAt": "2024-06-06T15:02:30+08:00", "frequency": "ad-hoc", "sources": ["Infocomm Media Development Authority"], "managedBy": "Info-communications Media Development Authority", "childDatasets": ["d_d8644084f8b54f851a1acbb2f04d5089", "d_b2778a9e4532d57cb9201c68cb5f2238"]}, "datasetMetadata": [{"datasetId": "d_d8644084f8b54f851a1acbb2f04d5089", "createdAt": "2019-01-09T00:00:00+08:00", "name": "Wireless HotSpots (GEOJSON)", "collectionIds": ["239"], "format": "GEOJSON", "lastUpdatedAt": "2024-06-06T15:02:30+08:00", "managedBy": "Info-communications Media Development Authority"}, {"datasetId": "d_b2778a9e4532d57cb9201c68cb5f2238", "createdAt": "2015-03-10T00:00:00+08:00", "name": "Wireless HotSpots (KML)", "collectionIds": ["239"], "format": "KML", "lastUpdatedAt": "2024-06-06T14:55:06+08:00", "managedBy": "Info-communications Media Development Authority"}]}, "errorMsg": ""}